solcxir/__init__.py
solcxir/exceptions.py
solcxir/install.py
solcxir/main.py
solcxir/wrapper.py
solcxir/utils/__init__.py
solcxir/utils/lock.py
py_solc_x_ir-1.0.0.dist-info/LICENSE
py_solc_x_ir-1.0.0.dist-info/METADATA
py_solc_x_ir-1.0.0.dist-info/WHEEL
py_solc_x_ir-1.0.0.dist-info/top_level.txt
py_solc_x_ir-1.0.0.dist-info/RECORD
