Metadata-Version: 2.1
Name: py-solc-x-ir
Version: 1.0.0
Summary: Python wrapper and version management tool for the solc Solidity compiler with IR support.
Home-page: https://github.com/BlockyFile/py-solc-x-ir
Author: EpicMario71 (forked from py-solc-x by ApeWorX)
Author-email: info@epicmario71.com
License: MIT
Keywords: ethereum solidity solc
Classifier: Intended Audience :: Developers
Classifier: License :: OSI Approved :: MIT License
Classifier: Natural Language :: English
Classifier: Programming Language :: Python :: 3
Classifier: Programming Language :: Python :: 3.6
Classifier: Programming Language :: Python :: 3.7
Classifier: Programming Language :: Python :: 3.8
Classifier: Programming Language :: Python :: 3.9
Requires-Python: >=3.6, <4
License-File: LICENSE
Requires-Dist: requests (<3,>=2.19.0)
Requires-Dist: semantic-version (<3,>=2.8.1)
